<annotation>
	<folder>img</folder>
	<filename>tree_202_xh4_20200210082500.jpg</filename>
	<path>/Users/fala/project/荔枝/img/tree_202_xh4_20200210082500.jpg</path>
	<source>
		<database>Unknown</database>
	</source>
	<size>
		<width>2592</width>
		<height>1944</height>
		<depth>3</depth>
	</size>
	<segmented>0</segmented>
	<object>
		<name>抽穗期</name>
		<pose>Unspecified</pose>
		<truncated>0</truncated>
		<difficult>0</difficult>
		<bndbox>
			<xmin>2024</xmin>
			<ymin>790</ymin>
			<xmax>2075</xmax>
			<ymax>888</ymax>
		</bndbox>
	</object>
	<object>
		<name>抽穗期</name>
		<pose>Unspecified</pose>
		<truncated>0</truncated>
		<difficult>0</difficult>
		<bndbox>
			<xmin>2394</xmin>
			<ymin>37</ymin>
			<xmax>2455</xmax>
			<ymax>188</ymax>
		</bndbox>
	</object>
	<object>
		<name>抽穗期</name>
		<pose>Unspecified</pose>
		<truncated>1</truncated>
		<difficult>0</difficult>
		<bndbox>
			<xmin>2236</xmin>
			<ymin>1</ymin>
			<xmax>2290</xmax>
			<ymax>131</ymax>
		</bndbox>
	</object>
	<object>
		<name>抽穗期</name>
		<pose>Unspecified</pose>
		<truncated>1</truncated>
		<difficult>0</difficult>
		<bndbox>
			<xmin>2291</xmin>
			<ymin>1</ymin>
			<xmax>2336</xmax>
			<ymax>58</ymax>
		</bndbox>
	</object>
	<object>
		<name>新梢生长期</name>
		<pose>Unspecified</pose>
		<truncated>0</truncated>
		<difficult>0</difficult>
		<bndbox>
			<xmin>841</xmin>
			<ymin>1002</ymin>
			<xmax>1196</xmax>
			<ymax>1249</ymax>
		</bndbox>
	</object>
</annotation>
