<annotation>
	<folder>img</folder>
	<filename>tree_202_xh4_20200123152700.jpg</filename>
	<path>/Users/fala/project/荔枝/img/tree_202_xh4_20200123152700.jpg</path>
	<source>
		<database>Unknown</database>
	</source>
	<size>
		<width>2592</width>
		<height>1944</height>
		<depth>3</depth>
	</size>
	<segmented>0</segmented>
	<object>
		<name>抽穗期</name>
		<pose>Unspecified</pose>
		<truncated>0</truncated>
		<difficult>0</difficult>
		<bndbox>
			<xmin>2387</xmin>
			<ymin>161</ymin>
			<xmax>2415</xmax>
			<ymax>202</ymax>
		</bndbox>
	</object>
	<object>
		<name>抽穗期</name>
		<pose>Unspecified</pose>
		<truncated>0</truncated>
		<difficult>0</difficult>
		<bndbox>
			<xmin>2235</xmin>
			<ymin>85</ymin>
			<xmax>2269</xmax>
			<ymax>146</ymax>
		</bndbox>
	</object>
	<object>
		<name>新梢生长期</name>
		<pose>Unspecified</pose>
		<truncated>0</truncated>
		<difficult>0</difficult>
		<bndbox>
			<xmin>805</xmin>
			<ymin>1016</ymin>
			<xmax>1186</xmax>
			<ymax>1284</ymax>
		</bndbox>
	</object>
</annotation>
